{
    "@schemaVersion": "1.0",
    "name": "mij_dsm",
    "variables": [
        "mij/Interpreter.json",
        "mij/FilterException.json",
        "mij/io/WriterOutputPipe.json",
        "mij/parse/Convert.json",
        "mij/lex/Lexeme.json",
        "mij/Filter.json",
        "mij/io/MemoryInputPipe.json",
        "mij/ast/Node.json",
        "mij/bnf/MultExpr.json",
        "mij/bnf/LexExpr.json",
        "mij/Repository.json",
        "mij/ast/FuncExpr.json",
        "mij/bnf/ParamExpr.json",
        "mij/Console.json",
        "mij/parse/Parser.json",
        "mij/bnf/GrammarType.json",
        "mij/ast/Variable.json",
        "mij/ast/Number.json",
        "mij/lex/Lexer.json",
        "mij/io/MemoryOutputPipe.json",
        "mij/io/OutputPipe.json",
        "mij/bnf/UnaryExpr.json",
        "mij/ast/UnaryOperExpr.json",
        "mij/bnf/ExponExpr.json",
        "mij/bnf/ValueExpr.json",
        "mij/ast/TreeVisitor.json",
        "mij/io/MemoryBuffer.json",
        "mij/bnf/Node.json",
        "mij/io/InputPipe.json",
        "mij/io/ReaderInputPipe.json",
        "mij/lex/LexType.json",
        "mij/bnf/AddExpr.json",
        "mij/ast/OperExpr.json",
        "mij/io/Pipe.json"
    ],
    "cells": [
        {
            "src": 0,
            "dest": 1,
            "values": {
                "Create": 1.0,
                "Throw": 1.0
            }
        },
        {
            "src": 0,
            "dest": 4,
            "values": {
                "Call": 1.0
            }
        },
        {
            "src": 0,
            "dest": 5,
            "values": {
                "Implement": 1.0
            }
        },
        {
            "src": 0,
            "dest": 7,
            "values": {
                "Import": 1.0,
                "Use": 1.0,
                "Typed": 1.0,
                "Call": 1.0
            }
        },
        {
            "src": 0,
            "dest": 10,
            "values": {
                "Typed": 1.0,
                "Call": 1.0
            }
        },
        {
            "src": 0,
            "dest": 11,
            "values": {
                "Import": 1.0,
                "Typed": 1.0
            }
        },
        {
            "src": 0,
            "dest": 16,
            "values": {
                "Import": 1.0,
                "Use": 1.0,
                "Typed": 1.0
            }
        },
        {
            "src": 0,
            "dest": 17,
            "values": {
                "Import": 1.0,
                "Typed": 1.0
            }
        },
        {
            "src": 0,
            "dest": 20,
            "values": {
                "Import": 1.0,
                "Typed": 1.0,
                "Call": 1.0
            }
        },
        {
            "src": 0,
            "dest": 22,
            "values": {
                "Import": 1.0,
                "Typed": 1.0
            }
        },
        {
            "src": 0,
            "dest": 25,
            "values": {
                "Import": 1.0,
                "Implement": 1.0
            }
        },
        {
            "src": 0,
            "dest": 28,
            "values": {
                "Import": 1.0,
                "Call": 1.0,
                "Typed": 1.0
            }
        },
        {
            "src": 0,
            "dest": 32,
            "values": {
                "Import": 1.0,
                "Typed": 1.0
            }
        },
        {
            "src": 0,
            "dest": 33,
            "values": {
                "Call": 1.0
            }
        },
        {
            "src": 2,
            "dest": 20,
            "values": {
                "Implement": 1.0
            }
        },
        {
            "src": 3,
            "dest": 1,
            "values": {
                "Import": 1.0,
                "Throw": 1.0
            }
        },
        {
            "src": 3,
            "dest": 4,
            "values": {
                "Typed": 1.0,
                "Call": 1.0,
                "Import": 1.0
            }
        },
        {
            "src": 3,
            "dest": 5,
            "values": {
                "Implement": 1.0,
                "Import": 1.0
            }
        },
        {
            "src": 3,
            "dest": 7,
            "values": {
                "Typed": 1.0,
                "Use": 1.0,
                "Call": 1.0
            }
        },
        {
            "src": 3,
            "dest": 9,
            "values": {
                "Cast": 1.0,
                "Call": 1.0
            }
        },
        {
            "src": 3,
            "dest": 11,
            "values": {
                "Call": 1.0,
                "Import": 1.0,
                "Create": 1.0
            }
        },
        {
            "src": 3,
            "dest": 15,
            "values": {
                "Use": 1.0,
                "Import": 1.0
            }
        },
        {
            "src": 3,
            "dest": 16,
            "values": {
                "Create": 1.0
            }
        },
        {
            "src": 3,
            "dest": 17,
            "values": {
                "Create": 1.0
            }
        },
        {
            "src": 3,
            "dest": 20,
            "values": {
                "Call": 1.0,
                "Import": 1.0,
                "Typed": 1.0
            }
        },
        {
            "src": 3,
            "dest": 22,
            "values": {
                "Call": 1.0,
                "Import": 1.0,
                "Create": 1.0
            }
        },
        {
            "src": 3,
            "dest": 27,
            "values": {
                "Use": 1.0,
                "Call": 1.0,
                "Typed": 1.0
            }
        },
        {
            "src": 3,
            "dest": 28,
            "values": {
                "Typed": 1.0,
                "Import": 1.0,
                "Call": 1.0
            }
        },
        {
            "src": 3,
            "dest": 30,
            "values": {
                "Use": 1.0,
                "Import": 1.0
            }
        },
        {
            "src": 3,
            "dest": 32,
            "values": {
                "Create": 1.0,
                "Call": 1.0,
                "Import": 1.0
            }
        },
        {
            "src": 3,
            "dest": 33,
            "values": {
                "Call": 1.0
            }
        },
        {
            "src": 4,
            "dest": 30,
            "values": {
                "Use": 1.0,
                "Typed": 1.0,
                "Import": 1.0
            }
        },
        {
            "src": 5,
            "dest": 1,
            "values": {
                "Throw": 1.0
            }
        },
        {
            "src": 6,
            "dest": 26,
            "values": {
                "Typed": 1.0,
                "Call": 1.0
            }
        },
        {
            "src": 6,
            "dest": 28,
            "values": {
                "Implement": 1.0
            }
        },
        {
            "src": 7,
            "dest": 4,
            "values": {
                "Typed": 1.0,
                "Import": 1.0
            }
        },
        {
            "src": 7,
            "dest": 25,
            "values": {
                "Typed": 1.0
            }
        },
        {
            "src": 8,
            "dest": 9,
            "values": {
                "Typed": 1.0
            }
        },
        {
            "src": 8,
            "dest": 15,
            "values": {
                "Use": 1.0,
                "Typed": 1.0
            }
        },
        {
            "src": 8,
            "dest": 23,
            "values": {
                "Typed": 1.0
            }
        },
        {
            "src": 8,
            "dest": 27,
            "values": {
                "Extend": 1.0,
                "Call": 1.0
            }
        },
        {
            "src": 9,
            "dest": 4,
            "values": {
                "Typed": 1.0,
                "Import": 1.0
            }
        },
        {
            "src": 9,
            "dest": 15,
            "values": {
                "Use": 1.0,
                "Typed": 1.0
            }
        },
        {
            "src": 9,
            "dest": 27,
            "values": {
                "Extend": 1.0
            }
        },
        {
            "src": 11,
            "dest": 4,
            "values": {
                "Import": 1.0,
                "Typed": 1.0
            }
        },
        {
            "src": 11,
            "dest": 7,
            "values": {
                "Extend": 1.0,
                "Call": 1.0
            }
        },
        {
            "src": 11,
            "dest": 25,
            "values": {
                "Typed": 1.0,
                "Call": 1.0
            }
        },
        {
            "src": 12,
            "dest": 9,
            "values": {
                "Typed": 1.0
            }
        },
        {
            "src": 12,
            "dest": 15,
            "values": {
                "Use": 1.0,
                "Typed": 1.0
            }
        },
        {
            "src": 12,
            "dest": 27,
            "values": {
                "Extend": 1.0,
                "Call": 1.0
            }
        },
        {
            "src": 12,
            "dest": 31,
            "values": {
                "Typed": 1.0
            }
        },
        {
            "src": 13,
            "dest": 0,
            "values": {
                "Create": 1.0,
                "Call": 1.0
            }
        },
        {
            "src": 13,
            "dest": 1,
            "values": {
                "Typed": 1.0
            }
        },
        {
            "src": 13,
            "dest": 3,
            "values": {
                "Import": 1.0,
                "Create": 1.0,
                "Call": 1.0
            }
        },
        {
            "src": 13,
            "dest": 4,
            "values": {
                "Import": 1.0,
                "Use": 1.0
            }
        },
        {
            "src": 13,
            "dest": 5,
            "values": {
                "Typed": 1.0,
                "Call": 1.0
            }
        },
        {
            "src": 13,
            "dest": 6,
            "values": {
                "Import": 1.0,
                "Create": 1.0,
                "Call": 1.0
            }
        },
        {
            "src": 13,
            "dest": 7,
            "values": {
                "Use": 1.0
            }
        },
        {
            "src": 13,
            "dest": 14,
            "values": {
                "Import": 1.0,
                "Create": 1.0,
                "Call": 1.0
            }
        },
        {
            "src": 13,
            "dest": 18,
            "values": {
                "Import": 1.0,
                "Create": 1.0,
                "Call": 1.0
            }
        },
        {
            "src": 13,
            "dest": 19,
            "values": {
                "Import": 1.0,
                "Create": 1.0,
                "Call": 1.0
            }
        },
        {
            "src": 13,
            "dest": 20,
            "values": {
                "Import": 1.0,
                "Typed": 1.0
            }
        },
        {
            "src": 13,
            "dest": 26,
            "values": {
                "Import": 1.0,
                "Typed": 1.0,
                "Create": 1.0,
                "Call": 1.0
            }
        },
        {
            "src": 13,
            "dest": 27,
            "values": {
                "Use": 1.0
            }
        },
        {
            "src": 13,
            "dest": 28,
            "values": {
                "Import": 1.0,
                "Typed": 1.0,
                "Call": 1.0
            }
        },
        {
            "src": 13,
            "dest": 29,
            "values": {
                "Import": 1.0,
                "Create": 1.0,
                "Call": 1.0
            }
        },
        {
            "src": 13,
            "dest": 33,
            "values": {
                "Call": 1.0
            }
        },
        {
            "src": 14,
            "dest": 1,
            "values": {
                "Throw": 1.0,
                "Import": 1.0,
                "Create": 1.0
            }
        },
        {
            "src": 14,
            "dest": 4,
            "values": {
                "Import": 1.0,
                "Use": 1.0,
                "Typed": 1.0,
                "Call": 1.0
            }
        },
        {
            "src": 14,
            "dest": 5,
            "values": {
                "Import": 1.0,
                "Implement": 1.0
            }
        },
        {
            "src": 14,
            "dest": 8,
            "values": {
                "Import": 1.0,
                "Call": 1.0,
                "Create": 1.0
            }
        },
        {
            "src": 14,
            "dest": 9,
            "values": {
                "Import": 1.0,
                "Create": 1.0,
                "Call": 1.0
            }
        },
        {
            "src": 14,
            "dest": 12,
            "values": {
                "Import": 1.0,
                "Create": 1.0,
                "Call": 1.0
            }
        },
        {
            "src": 14,
            "dest": 20,
            "values": {
                "Typed": 1.0,
                "Import": 1.0,
                "Call": 1.0
            }
        },
        {
            "src": 14,
            "dest": 21,
            "values": {
                "Create": 1.0,
                "Import": 1.0,
                "Call": 1.0
            }
        },
        {
            "src": 14,
            "dest": 23,
            "values": {
                "Create": 1.0,
                "Import": 1.0,
                "Call": 1.0
            }
        },
        {
            "src": 14,
            "dest": 24,
            "values": {
                "Create": 1.0,
                "Import": 1.0,
                "Call": 1.0
            }
        },
        {
            "src": 14,
            "dest": 27,
            "values": {
                "Typed": 1.0,
                "Use": 1.0,
                "Import": 1.0,
                "Call": 1.0
            }
        },
        {
            "src": 14,
            "dest": 28,
            "values": {
                "Typed": 1.0,
                "Import": 1.0,
                "Call": 1.0
            }
        },
        {
            "src": 14,
            "dest": 31,
            "values": {
                "Create": 1.0,
                "Import": 1.0,
                "Call": 1.0
            }
        },
        {
            "src": 14,
            "dest": 33,
            "values": {
                "Call": 1.0
            }
        },
        {
            "src": 16,
            "dest": 4,
            "values": {
                "Typed": 1.0,
                "Import": 1.0
            }
        },
        {
            "src": 16,
            "dest": 7,
            "values": {
                "Extend": 1.0,
                "Call": 1.0
            }
        },
        {
            "src": 16,
            "dest": 25,
            "values": {
                "Typed": 1.0,
                "Call": 1.0
            }
        },
        {
            "src": 17,
            "dest": 4,
            "values": {
                "Typed": 1.0,
                "Import": 1.0
            }
        },
        {
            "src": 17,
            "dest": 7,
            "values": {
                "Extend": 1.0,
                "Call": 1.0
            }
        },
        {
            "src": 17,
            "dest": 25,
            "values": {
                "Typed": 1.0,
                "Call": 1.0
            }
        },
        {
            "src": 18,
            "dest": 1,
            "values": {
                "Import": 1.0,
                "Throw": 1.0,
                "Create": 1.0
            }
        },
        {
            "src": 18,
            "dest": 4,
            "values": {
                "Use": 1.0,
                "Create": 1.0,
                "Call": 1.0
            }
        },
        {
            "src": 18,
            "dest": 5,
            "values": {
                "Import": 1.0,
                "Implement": 1.0
            }
        },
        {
            "src": 18,
            "dest": 20,
            "values": {
                "Import": 1.0,
                "Call": 1.0,
                "Typed": 1.0
            }
        },
        {
            "src": 18,
            "dest": 28,
            "values": {
                "Import": 1.0,
                "Call": 1.0,
                "Typed": 1.0
            }
        },
        {
            "src": 18,
            "dest": 30,
            "values": {
                "Use": 1.0
            }
        },
        {
            "src": 18,
            "dest": 33,
            "values": {
                "Call": 1.0
            }
        },
        {
            "src": 19,
            "dest": 20,
            "values": {
                "Implement": 1.0
            }
        },
        {
            "src": 19,
            "dest": 26,
            "values": {
                "Call": 1.0,
                "Typed": 1.0
            }
        },
        {
            "src": 20,
            "dest": 33,
            "values": {
                "Extend": 1.0
            }
        },
        {
            "src": 21,
            "dest": 9,
            "values": {
                "Typed": 1.0
            }
        },
        {
            "src": 21,
            "dest": 15,
            "values": {
                "Use": 1.0,
                "Typed": 1.0
            }
        },
        {
            "src": 21,
            "dest": 24,
            "values": {
                "Typed": 1.0
            }
        },
        {
            "src": 21,
            "dest": 27,
            "values": {
                "Extend": 1.0,
                "Call": 1.0
            }
        },
        {
            "src": 22,
            "dest": 4,
            "values": {
                "Import": 1.0,
                "Typed": 1.0
            }
        },
        {
            "src": 22,
            "dest": 7,
            "values": {
                "Call": 1.0,
                "Typed": 1.0,
                "Extend": 1.0
            }
        },
        {
            "src": 22,
            "dest": 25,
            "values": {
                "Call": 1.0,
                "Typed": 1.0
            }
        },
        {
            "src": 23,
            "dest": 9,
            "values": {
                "Typed": 1.0
            }
        },
        {
            "src": 23,
            "dest": 15,
            "values": {
                "Typed": 1.0,
                "Use": 1.0
            }
        },
        {
            "src": 23,
            "dest": 21,
            "values": {
                "Typed": 1.0
            }
        },
        {
            "src": 23,
            "dest": 27,
            "values": {
                "Extend": 1.0,
                "Call": 1.0
            }
        },
        {
            "src": 24,
            "dest": 9,
            "values": {
                "Typed": 1.0
            }
        },
        {
            "src": 24,
            "dest": 12,
            "values": {
                "Typed": 1.0
            }
        },
        {
            "src": 24,
            "dest": 15,
            "values": {
                "Typed": 1.0,
                "Use": 1.0
            }
        },
        {
            "src": 24,
            "dest": 27,
            "values": {
                "Call": 1.0,
                "Extend": 1.0
            }
        },
        {
            "src": 24,
            "dest": 31,
            "values": {
                "Typed": 1.0
            }
        },
        {
            "src": 25,
            "dest": 11,
            "values": {
                "Typed": 1.0
            }
        },
        {
            "src": 25,
            "dest": 16,
            "values": {
                "Typed": 1.0
            }
        },
        {
            "src": 25,
            "dest": 17,
            "values": {
                "Typed": 1.0
            }
        },
        {
            "src": 25,
            "dest": 22,
            "values": {
                "Typed": 1.0
            }
        },
        {
            "src": 25,
            "dest": 32,
            "values": {
                "Typed": 1.0
            }
        },
        {
            "src": 27,
            "dest": 15,
            "values": {
                "Typed": 1.0
            }
        },
        {
            "src": 28,
            "dest": 33,
            "values": {
                "Extend": 1.0
            }
        },
        {
            "src": 29,
            "dest": 28,
            "values": {
                "Implement": 1.0
            }
        },
        {
            "src": 31,
            "dest": 8,
            "values": {
                "Typed": 1.0
            }
        },
        {
            "src": 31,
            "dest": 9,
            "values": {
                "Typed": 1.0
            }
        },
        {
            "src": 31,
            "dest": 15,
            "values": {
                "Typed": 1.0,
                "Use": 1.0
            }
        },
        {
            "src": 31,
            "dest": 27,
            "values": {
                "Call": 1.0,
                "Extend": 1.0
            }
        },
        {
            "src": 32,
            "dest": 4,
            "values": {
                "Import": 1.0,
                "Typed": 1.0
            }
        },
        {
            "src": 32,
            "dest": 7,
            "values": {
                "Typed": 1.0,
                "Call": 1.0,
                "Extend": 1.0
            }
        },
        {
            "src": 32,
            "dest": 25,
            "values": {
                "Call": 1.0,
                "Typed": 1.0
            }
        }
    ]
}